jira2branch/__init__.py
jira2branch/__main__.py
jira2branch/tests/__init__.py
jira2branch/tests/test_main.py
jira2branch-0.6.1.dist-info/LICENSE
jira2branch-0.6.1.dist-info/METADATA
jira2branch-0.6.1.dist-info/WHEEL
jira2branch-0.6.1.dist-info/entry_points.txt
jira2branch-0.6.1.dist-info/RECORD
