Metadata-Version: 2.1
Name: jira2branch
Version: 0.6.1
Summary: Takes a JIRA issue and creates a git branch
License: MIT
Author: Tiago Pereira
Author-email: tiago@tiagoafpereira.net
Requires-Python: >=3.11,<3.12
Classifier: License :: OSI Approved :: MIT License
Classifier: Programming Language :: Python :: 3
Classifier: Programming Language :: Python :: 3.11
Requires-Dist: GitPython (==3.1.31)
Requires-Dist: Unidecode (==1.3.6)
Requires-Dist: click (==8.1.3)
Requires-Dist: halo (==0.0.31)
Requires-Dist: jira (==3.5.0)
Requires-Dist: platformdirs (>=4.3.6,<5.0.0)
Requires-Dist: python-gitlab (==3.14.0)
Requires-Dist: toml (>=0.10.2,<0.11.0)
